vsp_model_insight/__init__.py
vsp_model_insight/azuretable/__init__.py
vsp_model_insight/common/__init__.py
vsp_model_insight/common/protocol.py
vsp_model_insight/common/schedule.py
vsp_model_insight_azuretable-0.1.2.dist-info/METADATA
vsp_model_insight_azuretable-0.1.2.dist-info/WHEEL
vsp_model_insight_azuretable-0.1.2.dist-info/namespace_packages.txt
vsp_model_insight_azuretable-0.1.2.dist-info/top_level.txt
vsp_model_insight_azuretable-0.1.2.dist-info/RECORD
